selfpoc/_init_.py
selfpoc/mySeflJulianSum.py
mypackjulianpoc-1.3.dist-info/METADATA
mypackjulianpoc-1.3.dist-info/WHEEL
mypackjulianpoc-1.3.dist-info/top_level.txt
mypackjulianpoc-1.3.dist-info/RECORD
