Metadata-Version: 2.1
Name: mypackjulianpoc
Version: 1.3
Summary: A  module for test
Home-page: https://github.com/vfrtgb158/email
Author: Julian
Author-email: julian.zhang@pwc.com
License: MIT
Platform: UNKNOWN
